zklora/__init__.py
zklora/activations_commit.py
zklora/mpi_lora_onnx_exporter.py
zklora/polynomial_commit.py
zklora/zk_proof_generator.py
zklora/base_model_user_mpi/__init__.py
zklora/libs/merkle/Cargo.toml
zklora/libs/merkle/src/lib.rs
zklora/lora_contributor_mpi/__init__.py
zklora-0.2.dist-info/METADATA
zklora-0.2.dist-info/WHEEL
zklora-0.2.dist-info/RECORD
