Metadata-Version: 2.4
Name: zklora
Version: 0.2
Summary: A Python library for zero-knowledge proof generation and verification
Project-URL: Homepage, https://github.com/bagel-org/zklora
Project-URL: Bug Tracker, https://github.com/bagel-org/zklora/issues
Author-email: Bagel <team@bagel.net>
Classifier: License :: Other/Proprietary License
Classifier: Operating System :: OS Independent
Classifier: Programming Language :: Python :: 3
Requires-Python: >=3.8
Requires-Dist: blake3>=0.4.0
Requires-Dist: ezkl>=5.0.0
Requires-Dist: numpy>=1.24.0
Requires-Dist: onnx>=1.14.0
Requires-Dist: onnxruntime>=1.15.0
Requires-Dist: peft>=0.4.0
Requires-Dist: torch>=2.0.0
Requires-Dist: transformers>=4.30.0
